{
  "code": "05b97",
  "character": "宗",
  "variant": "Kaisho",
  "strokes": {
    "id": "",
    "groups": [
      {
        "id": "",
        "groups": [
          {
            "id": "",
            "groups": [],
            "strokes": [
              {
                "type": "㇔",
                "path": "M21.58,23.13c0,3.48-2.81,14.05-4.08,16.37",
                "numberPos": null
              },
              {
                "type": "㇖b",
                "path": "M23.27,25.24c8.8-0.99,55.73-4.53,62.87-4.9c11.15-0.59,2.36,7.16-0.42,9.28",
                "numberPos": null
              }
            ],
            "element": "冖"
          }
        ],
        "strokes": [
          {
            "type": "㇔",
            "path": "M49.45,9c3,1.5,8.57,6.15,9.42,9.04",
            "numberPos": null
          }
        ],
        "element": "宀",
        "position": "top",
        "radical": "general"
      },
      {
        "id": "",
        "groups": [
          {
            "id": "",
            "groups": [],
            "strokes": [
              {
                "type": "㇐",
                "path": "M34.37,40.69c0.74,0.3,2.11,0.38,2.85,0.3c4.74-0.52,28.28-2.99,33.3-3.08c1.24-0.02,1.98,0.14,2.6,0.3",
                "numberPos": null
              },
              {
                "type": "㇐",
                "path": "M21.81,58.45c1.2,0.43,3.41,0.51,4.61,0.43c9.08-0.63,42.33-4.63,56.98-4.64c2,0,3.21,0.21,4.21,0.42",
                "numberPos": null
              }
            ],
            "position": "top"
          },
          {
            "id": "",
            "groups": [],
            "strokes": [
              {
                "type": "㇚",
                "path": "M53.33,59.2c0.07,0.41,1.51,2.14,1.58,4.76c0.35,12.55,0.28,24.02,0.28,28.29c0,9.08-3.89,3.26-7.51,0.22",
                "numberPos": null
              },
              {
                "type": "㇒",
                "path": "M32.86,71.54c0.04,0.55,0.08,1.41-0.08,2.19c-0.98,4.62-8.12,13.64-15.87,19.84",
                "numberPos": null
              },
              {
                "type": "㇔",
                "path": "M73.99,71c6.28,3.63,16.53,14.52,18.09,20.17",
                "numberPos": null
              }
            ],
            "position": "bottom"
          }
        ],
        "strokes": [],
        "element": "示",
        "position": "bottom"
      }
    ],
    "strokes": [],
    "element": "宗"
  },
  "all_strokes": [
    {
      "type": "㇔",
      "path": "M49.45,9c3,1.5,8.57,6.15,9.42,9.04",
      "numberPos": null
    },
    {
      "type": "㇔",
      "path": "M21.58,23.13c0,3.48-2.81,14.05-4.08,16.37",
      "numberPos": null
    },
    {
      "type": "㇖b",
      "path": "M23.27,25.24c8.8-0.99,55.73-4.53,62.87-4.9c11.15-0.59,2.36,7.16-0.42,9.28",
      "numberPos": null
    },
    {
      "type": "㇐",
      "path": "M34.37,40.69c0.74,0.3,2.11,0.38,2.85,0.3c4.74-0.52,28.28-2.99,33.3-3.08c1.24-0.02,1.98,0.14,2.6,0.3",
      "numberPos": null
    },
    {
      "type": "㇐",
      "path": "M21.81,58.45c1.2,0.43,3.41,0.51,4.61,0.43c9.08-0.63,42.33-4.63,56.98-4.64c2,0,3.21,0.21,4.21,0.42",
      "numberPos": null
    },
    {
      "type": "㇚",
      "path": "M53.33,59.2c0.07,0.41,1.51,2.14,1.58,4.76c0.35,12.55,0.28,24.02,0.28,28.29c0,9.08-3.89,3.26-7.51,0.22",
      "numberPos": null
    },
    {
      "type": "㇒",
      "path": "M32.86,71.54c0.04,0.55,0.08,1.41-0.08,2.19c-0.98,4.62-8.12,13.64-15.87,19.84",
      "numberPos": null
    },
    {
      "type": "㇔",
      "path": "M73.99,71c6.28,3.63,16.53,14.52,18.09,20.17",
      "numberPos": null
    }
  ]
}