{
  "code": "06f15",
  "character": "漕",
  "variant": "Kaisho",
  "strokes": {
    "id": "",
    "groups": [
      {
        "id": "",
        "groups": [],
        "strokes": [
          {
            "type": "㇔",
            "path": "M18.38,17.25c4.19,1.56,10.82,6.41,11.87,8.84",
            "numberPos": null
          },
          {
            "type": "㇔",
            "path": "M14.25,44.25c3.97,1.37,10.26,5.62,11.25,7.75",
            "numberPos": null
          },
          {
            "type": "㇀",
            "path": "M14.75,90.21c1.75,0.04,3.81,0.36,4.75-1.25C22.25,84.25,26.5,75,29,69",
            "numberPos": null
          }
        ],
        "element": "氵",
        "original": "水",
        "variant": "true",
        "position": "left",
        "radical": "general"
      },
      {
        "id": "",
        "groups": [
          {
            "id": "",
            "groups": [
              {
                "id": "",
                "groups": [
                  {
                    "id": "",
                    "groups": [],
                    "strokes": [
                      {
                        "type": "㇑",
                        "path": "M40.74,34.39c0.34,0.59,1,1.85,1.1,2.63c0.32,2.57,4.11,20.94,4.22,21.73",
                        "numberPos": null
                      },
                      {
                        "type": "㇕",
                        "path": "M42.82,35.49c3.18-0.37,42.92-4.83,45.72-4.7c1.48,0.07,3.38,1.85,3.28,3.84c-0.26,5.04-5.23,20.18-5.89,21.31",
                        "numberPos": null
                      }
                    ],
                    "element": "日",
                    "part": 1
                  },
                  {
                    "id": "",
                    "groups": [
                      {
                        "id": "",
                        "groups": [
                          {
                            "id": "",
                            "groups": [],
                            "strokes": [
                              {
                                "type": "㇑",
                                "path": "M54.8,13.15c0.69,0.38,1.2,1.68,1.25,2.45c1.08,16.99,2.54,32.47,3.01,39.43",
                                "numberPos": null
                              }
                            ],
                            "element": "十",
                            "part": 1
                          }
                        ],
                        "strokes": [],
                        "element": "丿",
                        "variant": "true"
                      },
                      {
                        "id": "",
                        "groups": [
                          {
                            "id": "",
                            "groups": [],
                            "strokes": [
                              {
                                "type": "㇐",
                                "path": "M44.15,45.54c10.16-0.84,20.35-1.49,30.53-2.16c1.17-0.08,3.81-0.15,4.9-0.22",
                                "numberPos": null
                              }
                            ],
                            "element": "十",
                            "part": 2
                          }
                        ],
                        "strokes": [],
                        "element": "日",
                        "part": 2
                      }
                    ],
                    "strokes": [
                      {
                        "type": "㇑",
                        "path": "M73.06,10.25c0.69,0.38,1.29,1.68,1.25,2.44c-1.33,22.76-1.47,25.6-2.42,41.4",
                        "numberPos": null
                      },
                      {
                        "type": "㇐",
                        "path": "M47.41,56.29c5.38-0.38,31.35-2.42,38.05-2.75",
                        "numberPos": null
                      }
                    ],
                    "element": "廾",
                    "variant": "true"
                  }
                ],
                "strokes": [],
                "element": "曲"
              }
            ],
            "strokes": [
              {
                "type": "㇐",
                "path": "M37.58,24.02c1.09,0.46,3.09,0.56,4.2,0.46c11.16-0.98,38.06-4.59,49.55-3.95c1.82,0.1,2.92,0.22,3.83,0.45",
                "numberPos": null
              }
            ],
            "position": "top"
          },
          {
            "id": "",
            "groups": [],
            "strokes": [
              {
                "type": "㇑",
                "path": "M49.75,65.44c0.43,0.73,0.86,1.1,0.86,2.07s-0.29,29.06-0.29,29.54",
                "numberPos": null
              },
              {
                "type": "㇕a",
                "path": "M51.33,65.58c2.42-0.08,26.44-2.51,28.65-2.62c1.84-0.09,3.03,1.38,2.88,2.1c-0.29,1.44-1.12,29.85-1.12,30.58",
                "numberPos": null
              },
              {
                "type": "㇐a",
                "path": "M51.25,80.17c5,0.08,10.15-0.82,15.11-1.31c1.69-0.17,3.38-0.33,5-0.49",
                "numberPos": null
              },
              {
                "type": "㇐a",
                "path": "M51.6,94.3c6.68-0.42,21.36-1.56,29.68-1.88",
                "numberPos": null
              }
            ],
            "element": "日",
            "position": "bottom"
          }
        ],
        "strokes": [],
        "element": "曹",
        "position": "right"
      }
    ],
    "strokes": [],
    "element": "漕"
  },
  "all_strokes": [
    {
      "type": "㇔",
      "path": "M18.38,17.25c4.19,1.56,10.82,6.41,11.87,8.84",
      "numberPos": null
    },
    {
      "type": "㇔",
      "path": "M14.25,44.25c3.97,1.37,10.26,5.62,11.25,7.75",
      "numberPos": null
    },
    {
      "type": "㇀",
      "path": "M14.75,90.21c1.75,0.04,3.81,0.36,4.75-1.25C22.25,84.25,26.5,75,29,69",
      "numberPos": null
    },
    {
      "type": "㇐",
      "path": "M37.58,24.02c1.09,0.46,3.09,0.56,4.2,0.46c11.16-0.98,38.06-4.59,49.55-3.95c1.82,0.1,2.92,0.22,3.83,0.45",
      "numberPos": null
    },
    {
      "type": "㇑",
      "path": "M40.74,34.39c0.34,0.59,1,1.85,1.1,2.63c0.32,2.57,4.11,20.94,4.22,21.73",
      "numberPos": null
    },
    {
      "type": "㇕",
      "path": "M42.82,35.49c3.18-0.37,42.92-4.83,45.72-4.7c1.48,0.07,3.38,1.85,3.28,3.84c-0.26,5.04-5.23,20.18-5.89,21.31",
      "numberPos": null
    },
    {
      "type": "㇑",
      "path": "M54.8,13.15c0.69,0.38,1.2,1.68,1.25,2.45c1.08,16.99,2.54,32.47,3.01,39.43",
      "numberPos": null
    },
    {
      "type": "㇑",
      "path": "M73.06,10.25c0.69,0.38,1.29,1.68,1.25,2.44c-1.33,22.76-1.47,25.6-2.42,41.4",
      "numberPos": null
    },
    {
      "type": "㇐",
      "path": "M44.15,45.54c10.16-0.84,20.35-1.49,30.53-2.16c1.17-0.08,3.81-0.15,4.9-0.22",
      "numberPos": null
    },
    {
      "type": "㇐",
      "path": "M47.41,56.29c5.38-0.38,31.35-2.42,38.05-2.75",
      "numberPos": null
    },
    {
      "type": "㇑",
      "path": "M49.75,65.44c0.43,0.73,0.86,1.1,0.86,2.07s-0.29,29.06-0.29,29.54",
      "numberPos": null
    },
    {
      "type": "㇕a",
      "path": "M51.33,65.58c2.42-0.08,26.44-2.51,28.65-2.62c1.84-0.09,3.03,1.38,2.88,2.1c-0.29,1.44-1.12,29.85-1.12,30.58",
      "numberPos": null
    },
    {
      "type": "㇐a",
      "path": "M51.25,80.17c5,0.08,10.15-0.82,15.11-1.31c1.69-0.17,3.38-0.33,5-0.49",
      "numberPos": null
    },
    {
      "type": "㇐a",
      "path": "M51.6,94.3c6.68-0.42,21.36-1.56,29.68-1.88",
      "numberPos": null
    }
  ]
}