{
  "code": "05146",
  "character": "兆",
  "variant": "MidFst",
  "strokes": {
    "id": "",
    "groups": [
      {
        "id": "",
        "groups": [],
        "strokes": [
          {
            "type": "㇒",
            "path": "M39.75,18.25c0.5,0.75,0.88,3.76,0.88,5.06c0,8.19,0.06,21.19,0.06,30.21c0,26.99-6.21,34.15-15.44,42.23",
            "numberPos": null
          },
          {
            "type": "㇟",
            "path": "M58.49,11.87c0.74,1.19,1.33,2.59,1.38,4.43c0.2,8.19-0.03,61.64-0.03,67.2c0,13,8.9,12.03,17.67,12.03c9.25,0,15.34-1.68,16.64-2.62c2.75-2,2-3,2.25-6.5",
            "numberPos": null
          }
        ],
        "element": "儿",
        "original": "八",
        "part": 1,
        "position": "left",
        "radical": "tradit"
      },
      {
        "id": "",
        "groups": [],
        "strokes": [
          {
            "type": "㇔",
            "path": "M19,33.75c4.77,2.03,12.31,8.34,13.5,11.5",
            "numberPos": null
          },
          {
            "type": "㇀",
            "path": "M14.75,72.5c1.5,0.75,3,1,4.14,0.15C20.47,71.47,31.81,61.69,38,56",
            "numberPos": null
          }
        ],
        "element": "冫",
        "radical": "nelson"
      },
      {
        "id": "",
        "groups": [],
        "strokes": [
          {
            "type": "㇒",
            "path": "M84.76,23.64c0.04,0.38,0.09,0.99-0.09,1.54c-1.09,3.26-7.33,10.4-15.86,14.78",
            "numberPos": null
          },
          {
            "type": "㇔",
            "path": "M73,56c4.77,2.43,12.31,9.97,13.5,13.75",
            "numberPos": null
          }
        ],
        "position": "right"
      }
    ],
    "strokes": [],
    "element": "兆"
  },
  "all_strokes": [
    {
      "type": "㇒",
      "path": "M39.75,18.25c0.5,0.75,0.88,3.76,0.88,5.06c0,8.19,0.06,21.19,0.06,30.21c0,26.99-6.21,34.15-15.44,42.23",
      "numberPos": null
    },
    {
      "type": "㇟",
      "path": "M58.49,11.87c0.74,1.19,1.33,2.59,1.38,4.43c0.2,8.19-0.03,61.64-0.03,67.2c0,13,8.9,12.03,17.67,12.03c9.25,0,15.34-1.68,16.64-2.62c2.75-2,2-3,2.25-6.5",
      "numberPos": null
    },
    {
      "type": "㇔",
      "path": "M19,33.75c4.77,2.03,12.31,8.34,13.5,11.5",
      "numberPos": null
    },
    {
      "type": "㇀",
      "path": "M14.75,72.5c1.5,0.75,3,1,4.14,0.15C20.47,71.47,31.81,61.69,38,56",
      "numberPos": null
    },
    {
      "type": "㇒",
      "path": "M84.76,23.64c0.04,0.38,0.09,0.99-0.09,1.54c-1.09,3.26-7.33,10.4-15.86,14.78",
      "numberPos": null
    },
    {
      "type": "㇔",
      "path": "M73,56c4.77,2.43,12.31,9.97,13.5,13.75",
      "numberPos": null
    }
  ]
}