{
  "code": "07e54",
  "character": "織",
  "variant": "Kaisho",
  "strokes": {
    "id": "",
    "groups": [
      {
        "id": "",
        "groups": [],
        "strokes": [
          {
            "type": "㇜",
            "path": "M24.95,19.75c0.28,1.31,0.35,2.31-0.14,3.71c-2.49,7.08-5.44,12.2-8.45,18.12c-0.41,0.8-0.56,3.03,0,3.28c2.96,1.31,7.11,3.5,9.65,5.9",
            "numberPos": null
          },
          {
            "type": "㇜",
            "path": "M35.51,31.56c0.26,0.59,0.34,2.54,0,3.17c-5.02,9.3-12.51,22.25-19.4,30.73c-1.58,1.95,0.39,3.06,1.42,2.66c4.31-1.65,13.27-4.61,18.81-6.19",
            "numberPos": null
          },
          {
            "type": "㇔",
            "path": "M32.76,54.27c2.24,2.38,5.79,9.78,6.35,13.48",
            "numberPos": null
          },
          {
            "type": "㇔",
            "path": "M11.89,80.17c3.4,2.97,6.01,9.89,6.81,12.58",
            "numberPos": null
          },
          {
            "type": "㇔",
            "path": "M21.64,76.33c3.86,2.58,6.82,8.57,7.71,10.9",
            "numberPos": null
          },
          {
            "type": "㇔",
            "path": "M31.4,71.76c3.74,2.07,6.62,6.87,7.49,8.74",
            "numberPos": null
          }
        ],
        "element": "糸",
        "variant": "true",
        "position": "left",
        "radical": "general"
      },
      {
        "id": "",
        "groups": [
          {
            "id": "",
            "groups": [
              {
                "id": "",
                "groups": [
                  {
                    "id": "",
                    "groups": [
                      {
                        "id": "",
                        "groups": [],
                        "strokes": [
                          {
                            "type": "㇐",
                            "path": "M39,50.5c1.03,0.09,2.23,0.03,3.23-0.13c16.52-2.63,34.27-4.88,49.43-6.37c1.69-0.17,3.57,0,4.6,0.54",
                            "numberPos": null
                          }
                        ],
                        "element": "弋",
                        "part": 1
                      }
                    ],
                    "strokes": [],
                    "element": "戈",
                    "part": 1
                  }
                ],
                "strokes": [
                  {
                    "type": "㇔/㇑a",
                    "path": "M50.75,14.75c2.75,1.5,5.29,4.95,6.1,7.78",
                    "numberPos": null
                  },
                  {
                    "type": "㇐",
                    "path": "M40.81,28.5c0.59,0.08,2.91,0.48,3.49,0.42C48,28.5,57.25,27,64.25,26.38c0.97-0.09,1.54-0.14,2.03-0.12",
                    "numberPos": null
                  },
                  {
                    "type": "㇔",
                    "path": "M45.41,36.25c2.54,3.4,4.06,7.67,4.43,10.06",
                    "numberPos": null
                  },
                  {
                    "type": "㇒",
                    "path": "M62.82,29c1.08,0.75,1.01,2.03,0.86,2.5c-1.51,4.75-3.9,12.79-5.02,15.5",
                    "numberPos": null
                  }
                ],
                "element": "立"
              },
              {
                "id": "",
                "groups": [
                  {
                    "id": "",
                    "groups": [],
                    "strokes": [
                      {
                        "type": "㇑",
                        "path": "M45.94,61.09c0.31,0.64,0.81,2.14,0.81,3.02s-0.21,22.68-0.21,23.12c0,0.44,0.13,0.63,0.13,1.52",
                        "numberPos": null
                      },
                      {
                        "type": "㇕a",
                        "path": "M47.28,62.32c1.78-0.23,15.35-2.21,16.92-2.75c1.57-0.54,2.4-0.27,2.3,0.84c-0.1,1.1-0.62,23.37-0.52,24.35c0.1,0.98,0.01,1.12-0.26,2.21",
                        "numberPos": null
                      },
                      {
                        "type": "㇐a",
                        "path": "M47.59,74.17c2.4-0.16,8.83-1.57,11.54-1.75",
                        "numberPos": null
                      },
                      {
                        "type": "㇐a",
                        "path": "M47.28,86.43c3.55-0.23,13.06-1.73,17.65-2.03",
                        "numberPos": null
                      }
                    ],
                    "element": "日",
                    "position": "bottom"
                  }
                ],
                "strokes": [],
                "element": "音",
                "part": 2
              }
            ],
            "strokes": [],
            "position": "top"
          },
          {
            "id": "",
            "groups": [
              {
                "id": "",
                "groups": [],
                "strokes": [
                  {
                    "type": "㇂",
                    "path": "M71.74,13.5c1.07,1.79,1.63,2.28,1.74,6.15c0.8,29.46,9.09,64.8,21.53,75.81c4.23,3.75,3.61,0.77,3.08-7.17",
                    "numberPos": null
                  }
                ],
                "element": "弋",
                "part": 2
              },
              {
                "id": "",
                "groups": [],
                "strokes": [
                  {
                    "type": "㇒",
                    "path": "M90.75,54.15c0.05,0.74,0.11,1.9-0.1,2.96c-1.26,6.24-8.47,20.62-18.34,29",
                    "numberPos": null
                  }
                ],
                "element": "丿"
              },
              {
                "id": "",
                "groups": [
                  {
                    "id": "",
                    "groups": [],
                    "strokes": [
                      {
                        "type": "㇔",
                        "path": "M83.95,21.76c2.09,1.8,5.43,5.91,6.41,9",
                        "numberPos": null
                      }
                    ],
                    "element": "丶"
                  }
                ],
                "strokes": [],
                "element": "弋",
                "part": 3
              }
            ],
            "strokes": [],
            "element": "戈",
            "part": 2
          }
        ],
        "strokes": [],
        "element": "音",
        "part": 1,
        "position": "right"
      }
    ],
    "strokes": [],
    "element": "織"
  },
  "all_strokes": [
    {
      "type": "㇜",
      "path": "M24.95,19.75c0.28,1.31,0.35,2.31-0.14,3.71c-2.49,7.08-5.44,12.2-8.45,18.12c-0.41,0.8-0.56,3.03,0,3.28c2.96,1.31,7.11,3.5,9.65,5.9",
      "numberPos": null
    },
    {
      "type": "㇜",
      "path": "M35.51,31.56c0.26,0.59,0.34,2.54,0,3.17c-5.02,9.3-12.51,22.25-19.4,30.73c-1.58,1.95,0.39,3.06,1.42,2.66c4.31-1.65,13.27-4.61,18.81-6.19",
      "numberPos": null
    },
    {
      "type": "㇔",
      "path": "M32.76,54.27c2.24,2.38,5.79,9.78,6.35,13.48",
      "numberPos": null
    },
    {
      "type": "㇔",
      "path": "M11.89,80.17c3.4,2.97,6.01,9.89,6.81,12.58",
      "numberPos": null
    },
    {
      "type": "㇔",
      "path": "M21.64,76.33c3.86,2.58,6.82,8.57,7.71,10.9",
      "numberPos": null
    },
    {
      "type": "㇔",
      "path": "M31.4,71.76c3.74,2.07,6.62,6.87,7.49,8.74",
      "numberPos": null
    },
    {
      "type": "㇔/㇑a",
      "path": "M50.75,14.75c2.75,1.5,5.29,4.95,6.1,7.78",
      "numberPos": null
    },
    {
      "type": "㇐",
      "path": "M40.81,28.5c0.59,0.08,2.91,0.48,3.49,0.42C48,28.5,57.25,27,64.25,26.38c0.97-0.09,1.54-0.14,2.03-0.12",
      "numberPos": null
    },
    {
      "type": "㇔",
      "path": "M45.41,36.25c2.54,3.4,4.06,7.67,4.43,10.06",
      "numberPos": null
    },
    {
      "type": "㇒",
      "path": "M62.82,29c1.08,0.75,1.01,2.03,0.86,2.5c-1.51,4.75-3.9,12.79-5.02,15.5",
      "numberPos": null
    },
    {
      "type": "㇐",
      "path": "M39,50.5c1.03,0.09,2.23,0.03,3.23-0.13c16.52-2.63,34.27-4.88,49.43-6.37c1.69-0.17,3.57,0,4.6,0.54",
      "numberPos": null
    },
    {
      "type": "㇑",
      "path": "M45.94,61.09c0.31,0.64,0.81,2.14,0.81,3.02s-0.21,22.68-0.21,23.12c0,0.44,0.13,0.63,0.13,1.52",
      "numberPos": null
    },
    {
      "type": "㇕a",
      "path": "M47.28,62.32c1.78-0.23,15.35-2.21,16.92-2.75c1.57-0.54,2.4-0.27,2.3,0.84c-0.1,1.1-0.62,23.37-0.52,24.35c0.1,0.98,0.01,1.12-0.26,2.21",
      "numberPos": null
    },
    {
      "type": "㇐a",
      "path": "M47.59,74.17c2.4-0.16,8.83-1.57,11.54-1.75",
      "numberPos": null
    },
    {
      "type": "㇐a",
      "path": "M47.28,86.43c3.55-0.23,13.06-1.73,17.65-2.03",
      "numberPos": null
    },
    {
      "type": "㇂",
      "path": "M71.74,13.5c1.07,1.79,1.63,2.28,1.74,6.15c0.8,29.46,9.09,64.8,21.53,75.81c4.23,3.75,3.61,0.77,3.08-7.17",
      "numberPos": null
    },
    {
      "type": "㇒",
      "path": "M90.75,54.15c0.05,0.74,0.11,1.9-0.1,2.96c-1.26,6.24-8.47,20.62-18.34,29",
      "numberPos": null
    },
    {
      "type": "㇔",
      "path": "M83.95,21.76c2.09,1.8,5.43,5.91,6.41,9",
      "numberPos": null
    }
  ]
}